LICENSE
README.md
setup.py
pycalcy/__init__.py
pycalcy/__main__.py
pycalcy/astronomy.py
pycalcy/crypt.py
pycalcy/geometry.py
pycalcy/maths.py
pycalcy/physics.py
pycalcy/typical.py
pycalcy.egg-info/PKG-INFO
pycalcy.egg-info/SOURCES.txt
pycalcy.egg-info/dependency_links.txt
pycalcy.egg-info/top_level.txt