Metadata-Version: 2.1
Name: pycalcy
Version: 2.0.0
Summary: A pretty good globals calculation package for Python Development and more
Home-page: https://www.github.com/leoarayav/pycalcy
Author: Leo Araya
License: MIT
Keywords: pycalcy,python,calculator,maths,physics,astronomy,package
Classifier: Development Status :: 3 - Alpha
Classifier: Intended Audience :: Developers
Classifier: Topic :: Scientific/Engineering :: Astronomy
Classifier: Topic :: Scientific/Engineering :: Mathematics
Classifier: Topic :: Scientific/Engineering :: Physics
Classifier: License :: OSI Approved :: MIT License
Classifier: Programming Language :: Python :: 3
License-File: LICENSE
